CHANGELOG.md
LICENSE
dlt_init_openapi/__init__.py
dlt_init_openapi/__main__.py
dlt_init_openapi/cli/__init__.py
dlt_init_openapi/cli/cli_endpoint_selection.py
dlt_init_openapi/config.py
dlt_init_openapi/detector/__init__.py
dlt_init_openapi/detector/base_detector.py
dlt_init_openapi/detector/default/__init__.py
dlt_init_openapi/detector/default/const.py
dlt_init_openapi/detector/default/primary_key.py
dlt_init_openapi/detector/default/utils.py
dlt_init_openapi/detector/default/warnings.py
dlt_init_openapi/exceptions.py
dlt_init_openapi/parser/__init__.py
dlt_init_openapi/parser/config.py
dlt_init_openapi/parser/const.py
dlt_init_openapi/parser/context.py
dlt_init_openapi/parser/endpoints.py
dlt_init_openapi/parser/errors.py
dlt_init_openapi/parser/info.py
dlt_init_openapi/parser/models.py
dlt_init_openapi/parser/openapi_parser.py
dlt_init_openapi/parser/pagination.py
dlt_init_openapi/parser/parameters.py
dlt_init_openapi/parser/properties/__init__.py
dlt_init_openapi/parser/properties/converter.py
dlt_init_openapi/parser/security.py
dlt_init_openapi/parser/types.py
dlt_init_openapi/py.typed
dlt_init_openapi/renderer/__init__.py
dlt_init_openapi/renderer/base_renderer.py
dlt_init_openapi/renderer/default/__init__.py
dlt_init_openapi/renderer/default/templates/README.md.j2
dlt_init_openapi/renderer/default/templates/dlt_config.toml.j2
dlt_init_openapi/renderer/default/templates/dlt_secrets.toml.j2
dlt_init_openapi/renderer/default/templates/gitignore.j2
dlt_init_openapi/renderer/default/templates/pipeline.py.j2
dlt_init_openapi/renderer/default/templates/requirements.txt.j2
dlt_init_openapi/renderer/default/templates/source.py.j2
dlt_init_openapi/typing.py
dlt_init_openapi/utils/__init__.py
dlt_init_openapi/utils/misc.py
dlt_init_openapi/utils/paths.py
dlt_init_openapi/utils/update_rest_api.py
dlt_init_openapi-0.1.0.dist-info/LICENSE
dlt_init_openapi-0.1.0.dist-info/METADATA
dlt_init_openapi-0.1.0.dist-info/WHEEL
dlt_init_openapi-0.1.0.dist-info/entry_points.txt
dlt_init_openapi-0.1.0.dist-info/RECORD
