Metadata-Version: 2.1
Name: dlt-init-openapi
Version: 0.1.0
Summary: Generate dlt Python clients from OpenAPI
Home-page: https://dlthub.com
License: MIT
Keywords: OpenAPI,Client,Generator
Author: David Scharf
Author-email: david@dlthub.com
Requires-Python: >=3.9,<3.13
Classifier: Development Status :: 3 - Alpha
Classifier: Intended Audience :: Developers
Classifier: License :: OSI Approved :: MIT License
Classifier: Operating System :: MacOS :: MacOS X
Classifier: Operating System :: Microsoft :: Windows
Classifier: Operating System :: POSIX :: Linux
Classifier: Programming Language :: Python :: 3
Classifier: Programming Language :: Python :: 3.9
Classifier: Programming Language :: Python :: 3.10
Classifier: Programming Language :: Python :: 3.11
Classifier: Programming Language :: Python :: 3.12
Classifier: Topic :: Software Development :: Code Generators
Classifier: Typing :: Typed
Requires-Dist: autoflake (>=1.4,<3.0.0)
Requires-Dist: black (>=23)
Requires-Dist: dlt[duckdb] (>=0.4.12,<0.5.0)
Requires-Dist: httpx (>=0.15.4,<0.25.0)
Requires-Dist: inflector (>=3.1.1,<4.0.0)
Requires-Dist: isort (>=5.0.5,<6.0.0)
Requires-Dist: jinja2 (>=3.0.0,<4.0.0)
Requires-Dist: loguru (>=0.7.2,<0.8.0)
Requires-Dist: openapi-schema-pydantic (>=1.2.4,<2.0.0)
Requires-Dist: pydantic (>=1.6.1,<2.0.0)
Requires-Dist: questionary (>=1.10.0,<2.0.0)
Requires-Dist: referencing (>=0.34.0,<0.35.0)
Requires-Dist: requests (>=2.30.0,<3.0.0)
Requires-Dist: typer (>=0.12.3,<0.13.0)
Project-URL: Repository, https://github.com/dlt-hub/dlt-init-openapi
